Metadata-Version: 2.1
Name: apxr
Version: 1.0.0
Summary: scalable & good async proxyscraper
Home-page: https://github.com/zukixa/apx
Author: zukixa
Author-email: 56563509+zukixa@users.noreply.github.com
Classifier: Programming Language :: Python :: 3
Classifier: License :: OSI Approved :: MIT License
Classifier: Operating System :: OS Independent
Requires-Python: >=3.6
License-File: LICENSE
Requires-Dist: lxml
Requires-Dist: aiohttp
